Metadata-Version: 2.1
Name: cf-wesgrh
Version: 0.3
Summary: Gaussian and Binomial distributions
Author-email: arinafim300999@mail.ru
